drone_sqlite_api/__init__.py
drone_sqlite_api/main.py
drone_sqlite_api-0.1.0.dist-info/METADATA
drone_sqlite_api-0.1.0.dist-info/WHEEL
drone_sqlite_api-0.1.0.dist-info/RECORD
