Metadata-Version: 2.4
Name: drone-sqlite-api
Version: 0.1.0
Summary: A SQLite API for drone data management
Author: Drone API Team
License-Expression: MIT
Classifier: License :: OSI Approved :: MIT License
Classifier: Operating System :: OS Independent
Classifier: Programming Language :: Python :: 3
Requires-Python: >=3.8
